human_friendly_opening_hours/__init__.py
human_friendly_opening_hours/main.py
human_friendly_opening_hours/tests/__init__.py
human_friendly_opening_hours-0.0.6.dist-info/LICENSE
human_friendly_opening_hours-0.0.6.dist-info/METADATA
human_friendly_opening_hours-0.0.6.dist-info/WHEEL
human_friendly_opening_hours-0.0.6.dist-info/top_level.txt
human_friendly_opening_hours-0.0.6.dist-info/RECORD
