Metadata-Version: 2.1
Name: human-friendly-opening-hours
Version: 0.0.6
Summary: A package used to render opening hours in a human-friendly format
Home-page: https://github.com/glenncalleja/human_friendly_opening_hours
Author: Glenn Calleja Frendo
Author-email: glenncal@gmail.com
License: UNKNOWN
Platform: UNKNOWN
Classifier: Programming Language :: Python :: 3
Classifier: License :: OSI Approved :: MIT License
Classifier: Operating System :: OS Independent
Requires-Python: >=3.6
